setup.py
NJFU/__init__.py
NJFU/gradcampp.py
NJFU/hello.py
NJFU/pcd.py
NJFU/utils.py
NJFU/visdom_json.py
NJFU/yolo.py
NJFU.egg-info/PKG-INFO
NJFU.egg-info/SOURCES.txt
NJFU.egg-info/dependency_links.txt
NJFU.egg-info/top_level.txt
njfu.egg-info/PKG-INFO
njfu.egg-info/SOURCES.txt
njfu.egg-info/dependency_links.txt
njfu.egg-info/top_level.txt